MANIFEST.in
readme.md
setup.py
bin/nwanime-dl
nwanime_dl/__init__.py
nwanime_dl/helper.py
nwanime_dl/makehtml.py
nwanime_dl/nwanime_dl.py
nwanime_dl/regexes.py
nwanime_dl.egg-info/PKG-INFO
nwanime_dl.egg-info/SOURCES.txt
nwanime_dl.egg-info/dependency_links.txt
nwanime_dl.egg-info/not-zip-safe
nwanime_dl.egg-info/pbr.json
nwanime_dl.egg-info/requires.txt
nwanime_dl.egg-info/top_level.txt