Metadata-Version: 1.1
Name: nwanime-dl
Version: 1.8.6.7.4
Summary: downloads anime from nwanime
Home-page: https://github.com/thekindlyone/nwanime-dl
Author: thekindlyone
Author-email: dodo.dodder@gmail.com
License: GNU GPL v2
Platform: UNKNOWN
Classifier: Development Status :: 4 - Beta
Classifier: Topic :: Utilities
Classifier: License :: OSI Approved :: GNU General Public License v2 or later (GPLv2+)
Classifier: Operating System :: POSIX :: Linux
Classifier: Programming Language :: Python :: 2.7
